README.md
requirements.txt
setup.py
cvplotlib/__init__.py
cvplotlib/_version.py
cvplotlib/configuration.py
cvplotlib.egg-info/PKG-INFO
cvplotlib.egg-info/SOURCES.txt
cvplotlib.egg-info/dependency_links.txt
cvplotlib.egg-info/not-zip-safe
cvplotlib.egg-info/top_level.txt
cvplotlib/data_source/__init__.py
cvplotlib/data_source/base.py
cvplotlib/data_source/collection_source.py
cvplotlib/data_source/db_source.py
cvplotlib/data_source/file_source.py
cvplotlib/plotter/__init__.py
cvplotlib/plotter/base.py
cvplotlib/plotter/box.py
cvplotlib/plotter/line.py
tests/__init__.py
tests/data_source_tests/__init__.py
tests/data_source_tests/collection_source.py
tests/data_source_tests/db_source.py
tests/data_source_tests/file_source.py