Metadata-Version: 1.0
Name: cvplotlib
Version: 0.1.0
Summary: simple argparse wrapper with some syntactic sugar
Home-page: UNKNOWN
Author: Dimitri Korsch, Christoph Theiß
Author-email: korschdima@gmail.com, theisz.cm@gmail.com
License: MIT License
Platform: UNKNOWN
